Scyland3D/Scyland3D.py
Scyland3D/__init__.py
Scyland3D/example/200118G_canicula_mediterranean_40_female_mature_lower_tooth04_4.pts
Scyland3D/example/200118G_canicula_mediterranean_40_female_mature_lower_tooth09_4.pts
Scyland3D/example/200118H_canicula_mediterranean_47_female_mature_upper_tooth04_3.pts
Scyland3D/example/200118H_canicula_mediterranean_47_female_mature_upper_tooth09_2.pts
Scyland3D/example/200118H_canicula_mediterranean_47_female_mature_upper_tooth15_3.pts
Scyland3D/test/landmarks_ref.csv
Scyland3D/test/landmarks_reordered_ref.csv
Scyland3D/test/landmarks_reversed_ref.csv
Scyland3D-1.1.0.dist-info/LICENSE
Scyland3D-1.1.0.dist-info/METADATA
Scyland3D-1.1.0.dist-info/WHEEL
Scyland3D-1.1.0.dist-info/entry_points.txt
Scyland3D-1.1.0.dist-info/top_level.txt
Scyland3D-1.1.0.dist-info/RECORD
