Metadata-Version: 2.1
Name: Scyland3D
Version: 1.1.0
Summary: A Python package for processing 3D landmarks
Home-page: https://github.com/ybayle/Scyland3D
Author: Fidji Berio and Yann Bayle
Author-email: bayle.yann@live.fr
License: LICENSE
Project-URL: Bug Reports, https://github.com/ybayle/Scyland3D/issues
Platform: UNKNOWN
Classifier: Development Status :: 5 - Production/Stable
Classifier: Programming Language :: Python :: 2
Classifier: Programming Language :: Python :: 3
Classifier: License :: OSI Approved :: MIT License
Classifier: Operating System :: OS Independent
Requires-Dist: numpy (>=1.13.3)
